[
    {
        "Trick Name": "Banana Peel Escape",
        "Tier": 3,
        "Points": 200
    },
    {
        "Trick Name": "Banana Peel Operation",
        "Tier": 4,
        "Points": 650
    },
    {
        "Trick Name": "Extreme Motorsport",
        "Tier": 7,
        "Points": 1285
    },
    {
        "Trick Name": "Food for Thought",
        "Tier": 1,
        "Points": 75
    },
    {
        "Trick Name": "Hard Zyzz Return",
        "Tier": 6,
        "Points": 1150
    },
    {
        "Trick Name": "Imaginary Country",
        "Tier": 7,
        "Points": 1225
    },
    {
        "Trick Name": "Imaginary Island",
        "Tier": 6,
        "Points": 1000
    },
    {
        "Trick Name": "Imaginary Mackerel",
        "Tier": 4,
        "Points": 650
    },
    {
        "Trick Name": "Imaginary Pond",
        "Tier": 6,
        "Points": 1050
    },
    {
        "Trick Name": "Imaginary Wall",
        "Tier": 3,
        "Points": 200
    },
    {
        "Trick Name": "Imaginary World",
        "Tier": 8,
        "Points": 1300
    },
    {
        "Trick Name": "King's Banana Return to Box",
        "Tier": 7,
        "Points": 1265
    },
    {
        "Trick Name": "Outrageous Tomato Rise",
        "Tier": 6,
        "Points": 1000
    },
    {
        "Trick Name": "Tomato Rise",
        "Tier": 5,
        "Points": 850
    },
    {
        "Trick Name": "Zyzz Return",
        "Tier": 6,
        "Points": 1000
    }
]